openmind_accelerate/__init__.py
openmind_accelerate/megatron_plugin/__init__.py
openmind_accelerate/megatron_plugin/accelerator.py
openmind_accelerate/megatron_plugin/dataclasses.py
openmind_accelerate/megatron_plugin/imports.py
openmind_accelerate/megatron_plugin/megatron_lm.py
openmind_accelerate/npu_plugin/__init__.py
openmind_accelerate/npu_plugin/megatron_extension/__init__.py
openmind_accelerate/npu_plugin/megatron_npu/__init__.py
openmind_accelerate-0.5.2.dist-info/METADATA
openmind_accelerate-0.5.2.dist-info/WHEEL
openmind_accelerate-0.5.2.dist-info/licenses/LICENSE
openmind_accelerate-0.5.2.dist-info/licenses/LICENSE-Apache-2.0
openmind_accelerate-0.5.2.dist-info/RECORD
