Metadata-Version: 2.3
Name: openmind_accelerate
Version: 0.5.2
Summary: The openmind-accelerate is a product which allows you to use NVIDIA Megatron-LM in accelerate framework.
Project-URL: Homepage, https://gitee.com/openmind-ai/openmind-accelerate
Project-URL: Repository, https://gitee.com/openmind-ai/openmind-accelerate
Author-email: The openmind-accelerate Team <contact@openmind.cn>
License: The following applies to all files unless otherwise noted:
License-File: LICENSE
License-File: LICENSE-Apache-2.0
Classifier: Development Status :: 1 - Planning
Classifier: Intended Audience :: Developers
Classifier: Intended Audience :: Education
Classifier: Intended Audience :: Science/Research
Classifier: License :: OSI Approved :: Mulan Permissive Software License v2 (MulanPSL-2.0)
Classifier: Operating System :: OS Independent
Classifier: Programming Language :: Python :: 3
Classifier: Programming Language :: Python :: 3.8
Classifier: Programming Language :: Python :: 3.9
Classifier: Programming Language :: Python :: 3.10
Classifier: Topic :: Scientific/Engineering :: Artificial Intelligence
Requires-Python: <3.11,>=3.8
Requires-Dist: accelerate==0.28.0
Requires-Dist: datasets==2.18.0
Requires-Dist: setuptools==69.5.1
Requires-Dist: torch-npu==2.1.0.post3
Requires-Dist: torch==2.1.0
Requires-Dist: transformers==4.39.2
Provides-Extra: lint
Requires-Dist: black; extra == 'lint'
Requires-Dist: ruff; extra == 'lint'
Provides-Extra: test
Requires-Dist: pytest; extra == 'test'
Requires-Dist: pytest-cov; extra == 'test'
